streamlit_pyvista/__init__.py
streamlit_pyvista/cli.py
streamlit_pyvista/helpers/__init__.py
streamlit_pyvista/helpers/cache.py
streamlit_pyvista/helpers/streamlit_pyvista_logging.py
streamlit_pyvista/helpers/utils.py
streamlit_pyvista/lazy_mesh.py
streamlit_pyvista/mesh_viewer_component.py
streamlit_pyvista/message_interface.py
streamlit_pyvista/proxy.py
streamlit_pyvista/server_managers/__init__.py
streamlit_pyvista/server_managers/server_manager.py
streamlit_pyvista/server_managers/server_manager_proxified.py
streamlit_pyvista/trame_viewers/__init__.py
streamlit_pyvista/trame_viewers/trame_advanced_viewer.py
streamlit_pyvista/trame_viewers/trame_backend.py
streamlit_pyvista/trame_viewers/trame_viewer.py
streamlit_pyvista-0.0.18.dist-info/LICENSE
streamlit_pyvista-0.0.18.dist-info/METADATA
streamlit_pyvista-0.0.18.dist-info/WHEEL
streamlit_pyvista-0.0.18.dist-info/entry_points.txt
streamlit_pyvista-0.0.18.dist-info/RECORD
