Metadata-Version: 2.3
Name: streamlit-pyvista
Version: 0.0.18
Summary: A Streamlit component that allow support for new PyVista viewer backend: Trame.
Home-page: https://gitlab.com/groups/dcsm
License: GPL-3.0-or-later
Author: Maxime Rochat
Author-email: rochat.max@gmail.com
Requires-Python: >=3.9.12,<4.0.0
Classifier: License :: OSI Approved :: GNU General Public License v3 or later (GPLv3+)
Classifier: Programming Language :: Python :: 3
Classifier: Programming Language :: Python :: 3.10
Classifier: Programming Language :: Python :: 3.11
Classifier: Programming Language :: Python :: 3.12
Classifier: Programming Language :: Python :: 3.13
Requires-Dist: APScheduler (>=3.10.4,<4.0.0)
Requires-Dist: Flask (>=3.0.3,<4.0.0)
Requires-Dist: aiohttp (>=3.9.3,<4.0.0)
Requires-Dist: flask-sock (>=0.7.0,<0.8.0)
Requires-Dist: protobuf (<=4.25.3)
Requires-Dist: pytest (>=7.2.1)
Requires-Dist: pyvista (>=0.43.3,<0.44.0)
Requires-Dist: requests (>=2.31.0,<3.0.0)
Requires-Dist: streamlit (>=1.37.0,<2.0.0)
Requires-Dist: trame (>=3.5.2,<4.0.0)
Requires-Dist: trame-client (>=2.16.1,<3.0.0)
Requires-Dist: trame-plotly (>=3.0.2,<4.0.0)
Requires-Dist: trame-server (>=2.17.2,<3.0.0)
Requires-Dist: trame-vtk (>=2.8.5,<3.0.0)
Requires-Dist: trame-vuetify (>=2.4.2,<3.0.0)
Requires-Dist: validators (>=0.28.0,<0.29.0)
Requires-Dist: vtk (>=9.3.1,<9.4.0)
Requires-Dist: websocket-client (>=1.8.0,<2.0.0)
Project-URL: Repository, https://gitlab.com/dcsm/streamlit-pyvista
